{
  "_class": "shapePath",
  "booleanOperation": -1,
  "clippingMaskMode": 0,
  "do_objectID": "856EEC52-B682-4EA1-9734-97CBF101F2A1",
  "edited": true,
  "exportOptions": {
    "_class": "exportOptions",
    "exportFormats": [
    ],
    "includedLayerIds": [
    ],
    "layerOptions": 0,
    "shouldTrim": false
  },
  "frame": {
    "_class": "rect",
    "constrainProportions": false,
    "height": 7.299560739556057,
    "width": 1.389707620758065,
    "x": -8.50927075185776e-15,
    "y": 105.7637866984862
  },
  "hasClippingMask": false,
  "isClosed": true,
  "isFixedToViewport": false,
  "isFlippedHorizontal": false,
  "isFlippedVertical": false,
  "isLocked": false,
  "isVisible": true,
  "layerListExpandedType": 0,
  "maintainScrollPosition": false,
  "name": "Path",
  "nameIsFixed": false,
  "pointRadiusBehaviour": 1,
  "points": [
    {
      "_class": "curvePoint",
      "cornerRadius": 0,
      "curveFrom": "{0.84636533224727117, 0.32975270506667903}",
      "curveMode": 4,
      "curveTo": "{0.85890488442026691, 0.0012085065751724041}",
      "hasCurveFrom": true,
      "hasCurveTo": false,
      "point": "{0.85890488442026691, 0.0012085065751724041}"
    },
    {
      "_class": "curvePoint",
      "cornerRadius": 0,
      "curveFrom": "{1, 0.98988944587550887}",
      "curveMode": 4,
      "curveTo": "{0.89393364829131394, 0.66235779917841708}",
      "hasCurveFrom": false,
      "hasCurveTo": true,
      "point": "{1, 0.98988944587550887}"
    },
    {
      "_class": "curvePoint",
      "cornerRadius": 0,
      "curveFrom": "{0.037603344964125818, 0.66877585267050721}",
      "curveMode": 4,
      "curveTo": "{0.14486961815860694, 1}",
      "hasCurveFrom": true,
      "hasCurveTo": false,
      "point": "{0.14486961815860694, 1}"
    },
    {
      "_class": "curvePoint",
      "cornerRadius": 0,
      "curveFrom": "{0.0018777322799006482, 0}",
      "curveMode": 4,
      "curveTo": "{-0.010404693860417213, 0.33232078153891986}",
      "hasCurveFrom": false,
      "hasCurveTo": true,
      "point": "{0.0018777322799006482, 0}"
    }
  ],
  "resizingConstraint": 63,
  "resizingType": 0,
  "rotation": 0,
  "shouldBreakMaskChain": false,
  "style": {
    "_class": "style",
    "blur": {
      "_class": "blur",
      "center": "{0.5, 0.5}",
      "isEnabled": false,
      "motionAngle": 0,
      "radius": 10,
      "saturation": 1,
      "type": 0
    },
    "borderOptions": {
      "_class": "borderOptions",
      "dashPattern": [
      ],
      "isEnabled": true,
      "lineCapStyle": 0,
      "lineJoinStyle": 0
    },
    "borders": [
    ],
    "colorControls": {
      "_class": "colorControls",
      "brightness": 0,
      "contrast": 1,
      "hue": 0,
      "isEnabled": false,
      "saturation": 1
    },
    "contextSettings": {
      "_class": "graphicsContextSettings",
      "blendMode": 0,
      "opacity": 1
    },
    "do_objectID": "9054FA2D-3731-4991-84F2-716AC7F12881",
    "endMarkerType": 0,
    "fills": [
    ],
    "innerShadows": [
    ],
    "miterLimit": 10,
    "shadows": [
    ],
    "startMarkerType": 0,
    "windingRule": 1
  }
}