{
  "_class": "artboard",
  "backgroundColor": {
    "_class": "color",
    "alpha": 1,
    "blue": 1,
    "green": 1,
    "red": 1
  },
  "booleanOperation": -1,
  "clippingMaskMode": 0,
  "do_objectID": "CE8B7E1B-45A1-4AA8-8073-0D0FAE611DDC",
  "exportOptions": {
    "_class": "exportOptions",
    "exportFormats": [
      {
        "_class": "exportFormat",
        "absoluteSize": 0,
        "fileFormat": "png",
        "name": "",
        "namingScheme": 0,
        "scale": 3,
        "visibleScaleType": 0
      }
    ],
    "includedLayerIds": [
    ],
    "layerOptions": 0,
    "shouldTrim": false
  },
  "frame": {
    "_class": "rect",
    "constrainProportions": false,
    "height": 1023,
    "width": 1024,
    "x": 993,
    "y": -1037
  },
  "groupLayout": {
    "_class": "MSImmutableFreeformGroupLayout"
  },
  "hasBackgroundColor": true,
  "hasClickThrough": false,
  "hasClippingMask": false,
  "horizontalRulerData": {
    "_class": "rulerData",
    "base": 0,
    "guides": [
    ]
  },
  "includeBackgroundColorInExport": true,
  "includeInCloudUpload": true,
  "isFixedToViewport": false,
  "isFlippedHorizontal": false,
  "isFlippedVertical": false,
  "isFlowHome": false,
  "isLocked": false,
  "isVisible": true,
  "layerListExpandedType": 1,
  "layers": [
    {
      "class": "group",
      "id": "2D03A358-E50B-400B-A105-2789B8B9FA5B"
    },
    {
      "class": "group",
      "id": "BA565276-BAC0-4163-9F4F-8D11EAE00952"
    },
    {
      "class": "symbolInstance",
      "id": "DF7DFA7D-36D9-4D5B-9555-A2F0BD0F21F7"
    },
    {
      "class": "rectangle",
      "id": "DA18C7AB-2858-488C-BAA7-30DE832143CB"
    },
    {
      "class": "group",
      "id": "FF6EC736-1A94-470D-84B4-66819F45996D"
    }
  ],
  "maintainScrollPosition": false,
  "name": "01-3_Contact",
  "nameIsFixed": true,
  "presetDictionary": {
    "allowResizedMatching": 0,
    "height": 1024,
    "name": "Desktop",
    "offersLandscapeVariant": 0,
    "width": 1024
  },
  "resizesContent": false,
  "resizingConstraint": 63,
  "resizingType": 0,
  "rotation": 0,
  "shouldBreakMaskChain": true,
  "style": {
    "_class": "style",
    "blur": {
      "_class": "blur",
      "center": "{0.5, 0.5}",
      "isEnabled": false,
      "motionAngle": 0,
      "radius": 10,
      "saturation": 1,
      "type": 0
    },
    "borderOptions": {
      "_class": "borderOptions",
      "dashPattern": [
      ],
      "isEnabled": true,
      "lineCapStyle": 0,
      "lineJoinStyle": 0
    },
    "borders": [
    ],
    "colorControls": {
      "_class": "colorControls",
      "brightness": 0,
      "contrast": 1,
      "hue": 0,
      "isEnabled": false,
      "saturation": 1
    },
    "contextSettings": {
      "_class": "graphicsContextSettings",
      "blendMode": 0,
      "opacity": 1
    },
    "do_objectID": "11AD89A6-62B5-4B93-B854-80420A9C697C",
    "endMarkerType": 0,
    "fills": [
    ],
    "innerShadows": [
    ],
    "miterLimit": 10,
    "shadows": [
    ],
    "startMarkerType": 0,
    "windingRule": 1
  },
  "verticalRulerData": {
    "_class": "rulerData",
    "base": 0,
    "guides": [
    ]
  }
}